{
	"storyName": "Sayori/Natsuki",
	"difficulties": "",
	"hideFreeplay": false,
	"weekBackground": "sayonat",
	"freeplayColor": [
		146,
		113,
		253
	],
	"weekBefore": "tutorial",
	"startUnlocked": true,
	"weekCharacters": [
		"dad",
		"bf",
		"gf"
	],
	"songs": [
		[
			"Rain-Clouds",
			"sayori",
			[
				0,
				200,
				255
			]
		],
		[
			"My-Confession",
			"sayori",
			[
				0,
				200,
				255
			]
		],
		[
			"My-Sweets",
			"natsuki",
			[
				255,
				135,
				206
			]
		],
		[
			"Baka",
			"natsuki",
			[
				255,
				135,
				206
			]
		]
	],
	"hideStoryMode": false,
	"weekName": "Sayori/Natsuki"
}